[

  {
    "name": "Taposh",
    "phone": "54152105210"
  },
  {
    "name": "Pial",
    "phone": "87845545241"
  },
  {
    "name": "Sagor",
    "phone": "124154252"
  },  {
  "name": "Shamim",
  "phone": "65415418"
},  {
  "name": "Faruk",
  "phone": "785415215"
},  {
  "name": "Abdullah",
  "phone": "01485741521"
},  {
  "name": "Mannan",
  "phone": "018415215"
},  {
  "name": "Aziz",
  "phone": "0241852410"
},
  {
    "name": "Sazzad",
    "phone": "0241852410"
  },
  {
    "name": "Galib",
    "phone": "01541852"
  },

  {
    "name": "Taposh",
    "phone": "54152105210"
  },
  {
    "name": "Pial",
    "phone": "87845545241"
  },
  {
    "name": "Sagor",
    "phone": "124154252"
  },  {
  "name": "Shamim",
  "phone": "65415418"
},  {
  "name": "Faruk",
  "phone": "785415215"
},  {
  "name": "Abdullah",
  "phone": "01485741521"
},  {
  "name": "Mannan",
  "phone": "018415215"
},  {
  "name": "Aziz",
  "phone": "0241852410"
},
  {
    "name": "Sazzad",
    "phone": "0241852410"
  },
  {
    "name": "Galib",
    "phone": "01541852"
  },

  {
    "name": "Taposh",
    "phone": "54152105210"
  },
  {
    "name": "Pial",
    "phone": "87845545241"
  },
  {
    "name": "Sagor",
    "phone": "124154252"
  },  {
  "name": "Shamim",
  "phone": "65415418"
},  {
  "name": "Faruk",
  "phone": "785415215"
},  {
  "name": "Abdullah",
  "phone": "01485741521"
},  {
  "name": "Mannan",
  "phone": "018415215"
},  {
  "name": "Aziz",
  "phone": "0241852410"
},
  {
    "name": "Sazzad",
    "phone": "0241852410"
  },
  {
    "name": "Galib",
    "phone": "01541852"
  },

  {
    "name": "Taposh",
    "phone": "54152105210"
  },
  {
    "name": "Pial",
    "phone": "87845545241"
  },
  {
    "name": "Sagor",
    "phone": "124154252"
  },  {
  "name": "Shamim",
  "phone": "65415418"
},  {
  "name": "Faruk",
  "phone": "785415215"
},  {
  "name": "Abdullah",
  "phone": "01485741521"
},  {
  "name": "Mannan",
  "phone": "018415215"
},  {
  "name": "Aziz",
  "phone": "0241852410"
},
  {
    "name": "Sazzad",
    "phone": "0241852410"
  },
  {
    "name": "Galib",
    "phone": "01541852"
  }


]